{
  "Ink-Asia-2016": {
    "title": "Ink Asia 2016",
    "src": "/assets/exhibitions/image/Ink-Asia-2016.webp",
    "alt": "Ink Asia 2016",
    "metadata": {
        "title": "Zhang Zikang Ink Asia 2016",
        "description": "Zhang Zikang presented his artworks at Ink Asia 2016 in Hong Kong from December 16, 2016 to December 18, 2016",
        "keywords": "Zhang, Zikang, exhibition, Ink Asia 2016"
    },
    "detail": [
      {
        "title": "Ink Asia 2016",
        "img": "/assets/exhibitions/image/Ink-Asia-2016.webp",
        "alt": "Ink Asia 2016",
        "location": "Hong Kong",
        "dates": "December 16, 2016 - December 18, 2016"
      }
    ]
  },
  "11th-Florence-International-Biennale-of-Contemporary-Art": {
    "title": "11th Florence International Biennale of Contemporary Art",
    "src": "/assets/exhibitions/image/11th-Florence-International-Biennale-of-Contemporary-Art.webp",
    "alt": "11th Florence International Biennale of Contemporary Art",
    "metadata": {
        "title": "Zhang Zikang 11th Florence International Biennale of Contemporary Art",
        "description": "Zhang Zikang presented his artworks at 11th Florence International Biennale of Contemporary Art in Italy from October 6, 2017 to October 15, 2017",
        "keywords": "Zhang, Zikang, exhibition, 11th Florence International Biennale of Contemporary Art"
    },
    "detail": [
      {
        "title": "11th Florence International Biennale of Contemporary Art",
        "img": "/assets/exhibitions/image/11th-Florence-International-Biennale-of-Contemporary-Art.webp",
        "alt": "11th Florence International Biennale of Contemporary Art",
        "location": "Italy",
        "dates": "October 6, 2017 - October 15, 2017"
      }
    ]
  },
  "18th-Asian-BIEAF-International-Contemporary-Art-Invitational-Exhibition": {
    "title": "18th Asian BIEAF International Contemporary Art Invitational Exhibition",
    "src": "/assets/exhibitions/image/18th-Asian-BIEAF-International-Contemporary-Art-Invitational-Exhibition.webp",
    "alt": "18th Asian BIEAF International Contemporary Art Invitational Exhibition",
    "metadata": {
        "title": "Zhang Zikang 18th Asian BIEAF International Contemporary Art Invitational Exhibition",
        "description": "Zhang Zikang presented his artworks at 18th Asian BIEAF International Contemporary Art Invitational Exhibition in Korea from December 21, 2020 to December 26, 2020",
        "keywords": "Zhang, Zikang, exhibition, 18th Asian BIEAF International Contemporary Art Invitational Exhibition"
    },
    "detail": [
      {
        "title": "18th Asian BIEAF International Contemporary Art Invitational Exhibition",
        "img": "/assets/exhibitions/image/18th-Asian-BIEAF-International-Contemporary-Art-Invitational-Exhibition.webp",
        "alt": "18th Asian BIEAF International Contemporary Art Invitational Exhibition",
        "location": "Korea",
        "dates": "December 21, 2020 - December 26, 2020"
      }
    ]
  }
}
